ipyswiper/__init__.py
ipyswiper/__main__.py
ipyswiper/swiper.py
ipyswiper/templates/gallery_template.html
ipyswiper/templates/master_template.html
ipyswiper/templates/standalone_template.html
ipyswiper-0.1.2.dist-info/WHEEL
ipyswiper-0.1.2.dist-info/METADATA
ipyswiper-0.1.2.dist-info/RECORD
