Metadata-Version: 2.4
Name: ipyswiper
Version: 0.1.2
Summary: A reusable interactive image swiper component for Jupyter Notebooks.
Author-email: "J.J. Lee" <lee.j.joon@gmail.com>
Requires-Dist: ipython>=7.0.0
Requires-Dist: jupyter>=1.0.0
Requires-Dist: jinja2>=3.0.0
Requires-Dist: pytest ; extra == "test"
Provides-Extra: test
